mseep_unichat_mcp_server-0.2.23.dist-info/licenses/LICENSE
unichat_mcp_server/__init__.py
unichat_mcp_server/server.py
mseep_unichat_mcp_server-0.2.23.dist-info/METADATA
mseep_unichat_mcp_server-0.2.23.dist-info/WHEEL
mseep_unichat_mcp_server-0.2.23.dist-info/entry_points.txt
mseep_unichat_mcp_server-0.2.23.dist-info/top_level.txt
mseep_unichat_mcp_server-0.2.23.dist-info/RECORD
