Metadata-Version: 2.4
Name: mseep-unichat-mcp-server
Version: 0.2.23
Summary: Unichat MCP Server
Author-email: mseep <support@skydeck.ai>
Requires-Python: >=3.11
License-File: LICENSE
Requires-Dist: mcp>=1.0.0
Requires-Dist: unichat~=3.6.0
Dynamic: license-file
